<annotation><folder>..\input\train_xmls</folder><filename>00105.ppm</filename><path>./images00105.ppm</path><source><database>Unknown</database></source><size><width>1360</width><height>800</height><depth>3</depth></size><segmented>0</segmented><object><name>General caution</name><pose>Unspecified</pose><truncated>0</truncated><difficult>0</difficult><bndbox><xmin>256</xmin><ymin>438</ymin><xmax>303</xmax><ymax>484</ymax></bndbox></object><object><name>Traffic signals</name><pose>Unspecified</pose><truncated>0</truncated><difficult>0</difficult><bndbox><xmin>958</xmin><ymin>378</ymin><xmax>1024</xmax><ymax>440</ymax></bndbox></object></annotation>