<annotation><folder>..\input\train_xmls</folder><filename>00300.ppm</filename><path>./images00300.ppm</path><source><database>Unknown</database></source><size><width>1360</width><height>800</height><depth>3</depth></size><segmented>0</segmented><object><name>Road work</name><pose>Unspecified</pose><truncated>0</truncated><difficult>0</difficult><bndbox><xmin>680</xmin><ymin>430</ymin><xmax>710</xmax><ymax>458</ymax></bndbox></object><object><name>Speed limit (50km/h)</name><pose>Unspecified</pose><truncated>0</truncated><difficult>0</difficult><bndbox><xmin>779</xmin><ymin>420</ymin><xmax>801</xmax><ymax>443</ymax></bndbox></object></annotation>